{"numFailedTestSuites":0,"numFailedTests":0,"numPassedTestSuites":1,"numPassedTests":5,"numPendingTestSuites":0,"numPendingTests":0,"numRuntimeErrorTestSuites":0,"numTodoTests":0,"numTotalTestSuites":1,"numTotalTests":5,"openHandles":[],"snapshot":{"added":0,"didUpdate":false,"failure":false,"filesAdded":0,"filesRemoved":0,"filesRemovedList":[],"filesUnmatched":0,"filesUpdated":0,"matched":0,"total":0,"unchecked":0,"uncheckedKeysByFile":[],"unmatched":0,"updated":0},"startTime":1643004427087,"success":true,"testResults":[{"assertionResults":[{"ancestorTitles":["Sum 2 Numbers"],"failureMessages":[],"fullName":"Sum 2 Numbers User created a function called sum","location":null,"status":"passed","title":"User created a function called sum"},{"ancestorTitles":["Sum 2 Numbers"],"failureMessages":[],"fullName":"Sum 2 Numbers Function returns a number","location":null,"status":"passed","title":"Function returns a number"},{"ancestorTitles":["Sum 2 Numbers"],"failureMessages":[],"fullName":"Sum 2 Numbers sum(1, 2) returns 3","location":null,"status":"passed","title":"sum(1, 2) returns 3"},{"ancestorTitles":["Sum 2 Numbers"],"failureMessages":[],"fullName":"Sum 2 Numbers sum(5, 10) returns 15","location":null,"status":"passed","title":"sum(5, 10) returns 15"},{"ancestorTitles":["Sum 2 Numbers"],"failureMessages":[],"fullName":"Sum 2 Numbers sum(-1, -4) returns -5","location":null,"status":"passed","title":"sum(-1, -4) returns -5"}],"endTime":1643004427780,"message":"","name":"/Users/markmulligan/codingStuff/experiments/browser-code-editor-experiment/data/problem-1.test.js","startTime":1643004427187,"status":"passed","summary":""}],"wasInterrupted":false}